mestestdata/__init__.py
mestestdata/core.py
mestestdata-0.1.4.dist-info/METADATA
mestestdata-0.1.4.dist-info/WHEEL
mestestdata-0.1.4.dist-info/top_level.txt
mestestdata-0.1.4.dist-info/RECORD
